aco/__init__.py
aco-0.2.2.dist-info/WHEEL
aco-0.2.2.dist-info/METADATA
aco-0.2.2.dist-info/RECORD
